asgi_gssapi.py
ASGI_GSSAPI-0.1.2.dist-info/AUTHORS
ASGI_GSSAPI-0.1.2.dist-info/LICENSE
ASGI_GSSAPI-0.1.2.dist-info/METADATA
ASGI_GSSAPI-0.1.2.dist-info/WHEEL
ASGI_GSSAPI-0.1.2.dist-info/top_level.txt
ASGI_GSSAPI-0.1.2.dist-info/RECORD
