Metadata-Version: 2.1
Name: ASGI-GSSAPI
Version: 0.1.2
Summary: GSSAPI Kerberos authentication support in ASGI Middleware
Home-page: https://github.com/washed-out/asgi-gssapi
Author: Washed Out
Author-email: washed.out@outlook.com
License: BSD-3-Clause
Platform: any
Classifier: Development Status :: 4 - Beta
Classifier: Environment :: Web Environment
Classifier: Intended Audience :: Developers
Classifier: License :: OSI Approved :: BSD License
Classifier: Operating System :: OS Independent
Classifier: Programming Language :: Python
Classifier: Programming Language :: Python :: 3
Classifier: Topic :: Internet :: WWW/HTTP
Classifier: Topic :: Software Development :: Libraries :: Python Modules
License-File: LICENSE
License-File: AUTHORS
Requires-Dist: gssapi (>=1.7.0)
